ovos_vad_plugin_webrtcvad/__init__.py
ovos_vad_plugin_webrtcvad/version.py
ovos_vad_plugin_webrtcvad-0.0.1.dist-info/METADATA
ovos_vad_plugin_webrtcvad-0.0.1.dist-info/WHEEL
ovos_vad_plugin_webrtcvad-0.0.1.dist-info/entry_points.txt
ovos_vad_plugin_webrtcvad-0.0.1.dist-info/top_level.txt
ovos_vad_plugin_webrtcvad-0.0.1.dist-info/zip-safe
ovos_vad_plugin_webrtcvad-0.0.1.dist-info/RECORD
